llama_index/readers/firestore/__init__.py
llama_index/readers/firestore/base.py
llama_index_readers_firestore-0.4.1.dist-info/METADATA
llama_index_readers_firestore-0.4.1.dist-info/WHEEL
llama_index_readers_firestore-0.4.1.dist-info/licenses/LICENSE
llama_index_readers_firestore-0.4.1.dist-info/RECORD
