Metadata-Version: 2.4
Name: llama-index-readers-firestore
Version: 0.4.1
Summary: llama-index readers firestore integration
Author-email: Your Name <you@example.com>
Maintainer: rayzhudev
License-Expression: MIT
License-File: LICENSE
Keywords: datastore,firestore
Requires-Python: <4.0,>=3.9
Requires-Dist: google-cloud-firestore<3,>=2.14.0
Requires-Dist: llama-index-core<0.15,>=0.13.0
